mousetools/__init__.py
mousetools/auth.py
mousetools/decorators.py
mousetools/enums.py
mousetools/api/__init__.py
mousetools/api/menu.py
mousetools/api/search.py
mousetools/channels/__init__.py
mousetools/channels/enums.py
mousetools/channels/manager.py
mousetools/channels/calendar/__init__.py
mousetools/channels/characters/__init__.py
mousetools/channels/facilities/__init__.py
mousetools/channels/facilities/enums.py
mousetools/channels/facilitystatus/__init__.py
mousetools/channels/forecastedwaittimes/__init__.py
mousetools/channels/today/__init__.py
mousetools/mixins/__init__.py
mousetools/mixins/couchbase.py
mousetools/mixins/disney.py
mousetools/resources/environments.bin
mousetools-4.5.1.dist-info/licenses/LICENSE
mousetools-4.5.1.dist-info/METADATA
mousetools-4.5.1.dist-info/WHEEL
mousetools-4.5.1.dist-info/top_level.txt
mousetools-4.5.1.dist-info/RECORD
