Metadata-Version: 2.4
Name: mousetools
Version: 4.5.1
Summary: An unofficial Python wrapper for Disney's API
Author: Scott Caratozzolo
License-Expression: MIT
Project-URL: repository, https://gitlab.com/caratozzoloxyz/public/MouseTools
Project-URL: documentation, https://caratozzoloxyz.gitlab.io/public/MouseTools/
Project-URL: issues, https://gitlab.com/caratozzoloxyz/public/MouseTools/-/issues
Classifier: Programming Language :: Python :: 3
Classifier: Programming Language :: Python :: 3.9
Classifier: Programming Language :: Python :: 3.10
Classifier: Programming Language :: Python :: 3.11
Classifier: Programming Language :: Python :: 3.12
Classifier: Programming Language :: Python :: 3.13
Classifier: Operating System :: OS Independent
Requires-Python: <4.0,>=3.9
License-File: LICENSE
Requires-Dist: more-itertools>=10.7.0
Requires-Dist: pycryptodome>=3.22.0
Requires-Dist: python-dateutil>=2.9.0.post0
Requires-Dist: requests>=2.32.3
Requires-Dist: tzdata>=2025.2
Dynamic: license-file
